[
{
"yt_id": "LaHprcJcMbc",
"youtube_id": "LaHprcJcMbc",
"title": "Russia 4K - From Saint Petersburg to Kamchatka | Cinematic Drone Footage",
"description": "Russia 4K \u2014 Saint Petersburg to Kamchatka",
"tags": [
"landscape",
"russia",
"cinematic"
],
"category": "landscape",
"source": "youtube",
"status": "published",
"youtube_channel": "Explore The World 4K",
"lat": 59.70795,
"lon": 69.3148,
"shot_lat": 59.70795,
"shot_lon": 69.3148,
"thumb_url": "https://i.ytimg.com/vi/LaHprcJcMbc/maxresdefault.jpg",
"ai_quality_score": 7,
"duration_s": 0,
"price_usd": 0,
"resolution": "HD",
"published_at": "2026-01-24T23:25:20.093248Z"
},
{
"yt_id": "3OLn7XpaxJ0",
"youtube_id": "3OLn7XpaxJ0",
"title": "Lake Baikal 4K - World's Deepest Lake | Cinematic Drone Footage",
"description": "Lake Baikal 4K \u2014 Worlds Deepest Lake",
"tags": [
"ocean",
"baikal",
"lake",
"russia"
],
"category": "ocean",
"source": "youtube",
"status": "published",
"youtube_channel": "Explore The World 4K",
"lat": 54.18765,
"lon": 108.77985,
"shot_lat": 54.18765,
"shot_lon": 108.77985,
"thumb_url": "https://i.ytimg.com/vi/3OLn7XpaxJ0/maxresdefault.jpg",
"ai_quality_score": 7,
"duration_s": 0,
"price_usd": 0,
"resolution": "HD",
"published_at": "2025-08-07T16:56:20.093248Z"
},
{
"yt_id": "E6G-aHPGC60",
"youtube_id": "E6G-aHPGC60",
"title": "Explore the Breathtaking Sight of Lake Baikal, Siberia! (4K Aerial/Drone Video)",
"description": "LAKE BAIKAL Siberia Russia \u2014 Landscape 4K",
"tags": [
"landscape",
"baikal",
"siberia",
"russia"
],
"category": "landscape",
"source": "youtube",
"status": "published",
"youtube_channel": "Mind Travels",
"lat": 52.80795,
"lon": 107.1267,
"shot_lat": 52.80795,
"shot_lon": 107.1267,
"thumb_url": "https://i.ytimg.com/vi/E6G-aHPGC60/maxresdefault.jpg",
"ai_quality_score": 7,
"duration_s": 0,
"price_usd": 0,
"resolution": "HD",
"published_at": "2026-03-01T08:05:20.093248Z"
},
{
"yt_id": "hpyaWXjs_WQ",
"youtube_id": "hpyaWXjs_WQ",
"title": "Siberia 4K - The Untouched Wilderness of Remote Russia | Cinematic Drone Footage",
"description": "Siberia 4K \u2014 Untouched Wilderness of Remote Russia",
"tags": [
"landscape",
"siberia",
"russia",
"wilderness"
],
"category": "landscape",
"source": "youtube",
"status": "published",
"youtube_channel": "Explore The World 4K",
"lat": 60.05715,
"lon": 100.34905,
"shot_lat": 60.05715,
"shot_lon": 100.34905,
"thumb_url": "https://i.ytimg.com/vi/hpyaWXjs_WQ/maxresdefault.jpg",
"ai_quality_score": 7,
"duration_s": 0,
"price_usd": 0,
"resolution": "HD",
"published_at": "2025-05-22T05:06:32.093248Z"
},
{
"yt_id": "tlxQGcm3_uk",
"youtube_id": "tlxQGcm3_uk",
"title": "Lake Baikal, Russia \ud83c\uddf7\ud83c\uddfa - by drone [4K]",
"description": "Lake Baikal Russia \u2014 by drone 4K",
"tags": [
"ocean",
"baikal",
"russia"
],
"category": "ocean",
"source": "youtube",
"status": "published",
"youtube_channel": "Drone Snap",
"lat": 54.0338,
"lon": 108.73065,
"shot_lat": 54.0338,
"shot_lon": 108.73065,
"thumb_url": "https://i.ytimg.com/vi/tlxQGcm3_uk/maxresdefault.jpg",
"ai_quality_score": 7,
"duration_s": 0,
"price_usd": 0,
"resolution": "HD",
"published_at": "2025-06-25T09:44:41.093248Z"
},
{
"yt_id": "Vqdb8l_4mJ8",
"youtube_id": "Vqdb8l_4mJ8",
"title": "\u30104K\u3011Drone Footage | The Beauty of Russia in 18 Minutes 2019 | Cinematic Aerial Siberia | \u0420\u043e\u0441\u0441\u0438\u044f \u0414\u0440\u043e\u043d",
"description": "The Beauty of Russia in 18 Minutes \u2014 Siberia",
"tags": [
"landscape",
"russia",
"siberia",
"drone"
],
"category": "landscape",
"source": "youtube",
"status": "published",
"youtube_channel": "One Man Wolf Pack",
"lat": 56.312,
"lon": 91.5803,
"shot_lat": 56.312,
"shot_lon": 91.5803,
"thumb_url": "https://i.ytimg.com/vi/Vqdb8l_4mJ8/maxresdefault.jpg",
"ai_quality_score": 7,
"duration_s": 0,
"price_usd": 0,
"resolution": "HD",
"published_at": "2025-08-15T20:18:13.093248Z"
},
{
"yt_id": "J5wYV8O0E0U",
"youtube_id": "J5wYV8O0E0U",
"title": "Amazing Kamchatka, Russia in 4K Ultra HD - Incredible 4K Drone Footage - Earth Spirit",
"description": "Amazing Kamchatka Russia \u2014 4K Ultra HD",
"tags": [
"mountain",
"kamchatka",
"russia",
"volcano"
],
"category": "mountain",
"source": "youtube",
"status": "published",
"youtube_channel": "Earth Spirit",
"lat": 56.594,
"lon": 159.8638,
"shot_lat": 56.594,
"shot_lon": 159.8638,
"thumb_url": "https://i.ytimg.com/vi/J5wYV8O0E0U/maxresdefault.jpg",
"ai_quality_score": 7,
"duration_s": 0,
"price_usd": 0,
"resolution": "HD",
"published_at": "2026-04-17T19:33:33.093248Z"
},
{
"yt_id": "ETp-jv20fRQ",
"youtube_id": "ETp-jv20fRQ",
"title": "Kamchatka, Russia \ud83c\uddf7\ud83c\uddfa - by drone [4K]",
"description": "Kamchatka Russia \u2014 by drone 4K",
"tags": [
"mountain",
"kamchatka",
"russia"
],
"category": "mountain",
"source": "youtube",
"status": "published",
"youtube_channel": "Drone Snap",
"lat": 56.4316,
"lon": 159.54755,
"shot_lat": 56.4316,
"shot_lon": 159.54755,
"thumb_url": "https://i.ytimg.com/vi/ETp-jv20fRQ/maxresdefault.jpg",
"ai_quality_score": 7,
"duration_s": 0,
"price_usd": 0,
"resolution": "HD",
"published_at": "2025-10-01T05:00:29.093248Z"
},
{
"yt_id": "hl4lRGdVUz4",
"youtube_id": "hl4lRGdVUz4",
"title": "Beautiful Kamchatka, drone footage",
"description": "Beautiful Kamchatka \u2014 drone footage",
"tags": [
"mountain",
"kamchatka",
"russia"
],
"category": "mountain",
"source": "youtube",
"status": "published",
"youtube_channel": "alexcalive",
"lat": 56.3259,
"lon": 160.2429,
"shot_lat": 56.3259,
"shot_lon": 160.2429,
"thumb_url": "https://i.ytimg.com/vi/hl4lRGdVUz4/maxresdefault.jpg",
"ai_quality_score": 7,
"duration_s": 0,
"price_usd": 0,
"resolution": "HD",
"published_at": "2026-01-26T19:27:47.093248Z"
},
{
"yt_id": "6RyKxB8g_HY",
"youtube_id": "6RyKxB8g_HY",
"title": "\u30104K\u3011\ud83c\uddf2\ud83c\uddf3 Drone Footage \ud83d\udd25 Ulanbaatar - Capital of Mongolia \ud83d\udd25 Cinematic Aerial Film \ud83d\udd25 Ulan Bator",
"description": "Ulaanbaatar Capital of Mongolia 4K",
"tags": [
"cityscape",
"mongolia",
"ulaanbaatar",
"capital"
],
"category": "cityscape",
"source": "youtube",
"status": "published",
"youtube_channel": "One Man Wolf Pack",
"lat": 48.34855,
"lon": 106.21555,
"shot_lat": 48.34855,
"shot_lon": 106.21555,
"thumb_url": "https://i.ytimg.com/vi/6RyKxB8g_HY/maxresdefault.jpg",
"ai_quality_score": 7,
"duration_s": 0,
"price_usd": 0,
"resolution": "HD",
"published_at": "2025-09-08T17:41:32.093248Z"
},
{
"yt_id": "Z8gGBEv8_RE",
"youtube_id": "Z8gGBEv8_RE",
"title": "Amazing Mongolia | 4K | Drone footage",
"description": "Amazing Mongolia 4K \u2014 Drone Footage",
"tags": [
"landscape",
"mongolia",
"steppe"
],
"category": "landscape",
"source": "youtube",
"status": "published",
"youtube_channel": "LP Productions",
"lat": 45.8247,
"lon": 102.3838,
"shot_lat": 45.8247,
"shot_lon": 102.3838,
"thumb_url": "https://i.ytimg.com/vi/Z8gGBEv8_RE/maxresdefault.jpg",
"ai_quality_score": 7,
"duration_s": 0,
"price_usd": 0,
"resolution": "HD",
"published_at": "2025-12-05T22:47:55.093248Z"
},
{
"yt_id": "N1gwwKiEXrE",
"youtube_id": "N1gwwKiEXrE",
"title": "Ulaanbaatar, Mongolia \ud83c\uddf2\ud83c\uddf3 in 4K 60FPS ULTRA HD Video by Drone",
"description": "Ulaanbaatar Mongolia 4K 60FPS Ultra HD \u2014 Drone",
"tags": [
"cityscape",
"mongolia",
"ulaanbaatar"
],
"category": "cityscape",
"source": "youtube",
"status": "published",
"youtube_channel": "Exploropia",
"lat": 48.0833,
"lon": 106.47355,
"shot_lat": 48.0833,
"shot_lon": 106.47355,
"thumb_url": "https://i.ytimg.com/vi/N1gwwKiEXrE/maxresdefault.jpg",
"ai_quality_score": 7,
"duration_s": 0,
"price_usd": 0,
"resolution": "HD",
"published_at": "2025-10-08T05:05:51.093248Z"
},
{
"yt_id": "X8biCcI1W7g",
"youtube_id": "X8biCcI1W7g",
"title": "Ulaanbaatar, Mongolia \ud83c\uddf2\ud83c\uddf3 4K 60fps  Drone Footage",
"description": "Ulaanbaatar Mongolia 4K 60fps \u2014 Drone Footage",
"tags": [
"cityscape",
"mongolia",
"ulaanbaatar"
],
"category": "cityscape",
"source": "youtube",
"status": "published",
"youtube_channel": "Ace Travel",
"lat": 47.3769,
"lon": 106.71855,
"shot_lat": 47.3769,
"shot_lon": 106.71855,
"thumb_url": "https://i.ytimg.com/vi/X8biCcI1W7g/maxresdefault.jpg",
"ai_quality_score": 7,
"duration_s": 0,
"price_usd": 0,
"resolution": "HD",
"published_at": "2025-12-13T09:28:47.093248Z"
},
{
"yt_id": "ZGE_24A3K8Q",
"youtube_id": "ZGE_24A3K8Q",
"title": "Ulaanbaatar, Mongolia \ud83c\uddf2\ud83c\uddf3 | 4K Drone Footage",
"description": "Ulaanbaatar Mongolia \u2014 4K Drone Footage",
"tags": [
"cityscape",
"mongolia",
"ulaanbaatar"
],
"category": "cityscape",
"source": "youtube",
"status": "published",
"youtube_channel": "MTI Aerials",
"lat": 47.46205,
"lon": 107.15585,
"shot_lat": 47.46205,
"shot_lon": 107.15585,
"thumb_url": "https://i.ytimg.com/vi/ZGE_24A3K8Q/maxresdefault.jpg",
"ai_quality_score": 7,
"duration_s": 0,
"price_usd": 0,
"resolution": "HD",
"published_at": "2026-03-31T22:00:26.093248Z"
},
{
"yt_id": "MpddTbiDygA",
"youtube_id": "MpddTbiDygA",
"title": "Highlights of Mongolia from Above | Drone | DJI Mavic Pro | 4K",
"description": "Highlights of Mongolia from Above \u2014 DJI Mavic Pro 4K",
"tags": [
"landscape",
"mongolia",
"steppe",
"gobi"
],
"category": "landscape",
"source": "youtube",
"status": "published",
"youtube_channel": "Drink Tea & Travel",
"lat": 43.5269,
"lon": 104.24805,
"shot_lat": 43.5269,
"shot_lon": 104.24805,
"thumb_url": "https://i.ytimg.com/vi/MpddTbiDygA/maxresdefault.jpg",
"ai_quality_score": 7,
"duration_s": 0,
"price_usd": 0,
"resolution": "HD",
"published_at": "2025-10-24T03:52:07.093248Z"
},
{
"yt_id": "XhfipkDjYdc",
"youtube_id": "XhfipkDjYdc",
"title": "\u30104K\u3011\ud83c\uddf2\ud83c\uddf3 Ulan Bator from Above \ud83d\udd25 MONGOLIA 2022 \ud83d\udd25 Cinematic Wolf Aerial\u2122 Drone Film",
"description": "Ulan Bator from Above Mongolia 2022 \u2014 Cinematic Wolf Aerial",
"tags": [
"cityscape",
"mongolia",
"ulaanbaatar"
],
"category": "cityscape",
"source": "youtube",
"status": "published",
"youtube_channel": "One Man Wolf Pack",
"lat": 47.9345,
"lon": 106.333,
"shot_lat": 47.9345,
"shot_lon": 106.333,
"thumb_url": "https://i.ytimg.com/vi/XhfipkDjYdc/maxresdefault.jpg",
"ai_quality_score": 7,
"duration_s": 0,
"price_usd": 0,
"resolution": "HD",
"published_at": "2026-04-18T02:49:03.093248Z"
},
{
"yt_id": "9_CrEwQ_rO4",
"youtube_id": "9_CrEwQ_rO4",
"title": "Mongolia in 4K ULTRA HD HDR Drone",
"description": "Mongolia in 4K Ultra HD HDR \u2014 Drone",
"tags": [
"landscape",
"mongolia",
"hdr"
],
"category": "landscape",
"source": "youtube",
"status": "published",
"youtube_channel": "Go Places Pro",
"lat": 47.43165,
"lon": 104.6663,
"shot_lat": 47.43165,
"shot_lon": 104.6663,
"thumb_url": "https://i.ytimg.com/vi/9_CrEwQ_rO4/maxresdefault.jpg",
"ai_quality_score": 7,
"duration_s": 0,
"price_usd": 0,
"resolution": "HD",
"published_at": "2026-03-28T05:29:22.093248Z"
},
{
"yt_id": "oRmGrPobEvI",
"youtube_id": "oRmGrPobEvI",
"title": "Tajikistan 4K - Hidden Gem of Central Asia | Cinematic Drone Footage",
"description": "Tajikistan 4K \u2014 Hidden Gem of Central Asia",
"tags": [
"mountain",
"tajikistan",
"pamir",
"central-asia"
],
"category": "mountain",
"source": "youtube",
"status": "published",
"youtube_channel": "Explore The World 4K",
"lat": 38.19965,
"lon": 68.07315,
"shot_lat": 38.19965,
"shot_lon": 68.07315,
"thumb_url": "https://i.ytimg.com/vi/oRmGrPobEvI/maxresdefault.jpg",
"ai_quality_score": 7,
"duration_s": 0,
"price_usd": 0,
"resolution": "HD",
"published_at": "2026-02-08T05:39:34.093248Z"
},
{
"yt_id": "mRiZMcBeb9I",
"youtube_id": "mRiZMcBeb9I",
"title": "\u30104K\u3011\ud83c\uddf9\ud83c\uddef Drone RAW Footage \ud83d\udd25 This is TAJIKISTAN 2025 \ud83d\udd25 Pamir Highway & Kazakhstan \ud83d\udd25UltraHD Stock Video",
"description": "Tajikistan + Pamir Highway + Kazakhstan \u2014 Drone 4K 2025",
"tags": [
"mountain",
"tajikistan",
"pamir",
"highway"
],
"category": "mountain",
"source": "youtube",
"status": "published",
"youtube_channel": "One Man Wolf Pack",
"lat": 38.73415,
"lon": 73.22305,
"shot_lat": 38.73415,
"shot_lon": 73.22305,
"thumb_url": "https://i.ytimg.com/vi/mRiZMcBeb9I/maxresdefault.jpg",
"ai_quality_score": 7,
"duration_s": 0,
"price_usd": 0,
"resolution": "HD",
"published_at": "2025-09-23T20:46:52.093248Z"
},
{
"yt_id": "jO07u6S3jdU",
"youtube_id": "jO07u6S3jdU",
"title": "Kyrgyzstan 4K - Wild Beauty of Central Asia | Cinematic Drone Footage",
"description": "Kyrgyzstan 4K \u2014 Wild Beauty of Central Asia",
"tags": [
"mountain",
"kyrgyzstan",
"central-asia"
],
"category": "mountain",
"source": "youtube",
"status": "published",
"youtube_channel": "Explore The World 4K",
"lat": 42.9301,
"lon": 74.75445,
"shot_lat": 42.9301,
"shot_lon": 74.75445,
"thumb_url": "https://i.ytimg.com/vi/jO07u6S3jdU/maxresdefault.jpg",
"ai_quality_score": 7,
"duration_s": 0,
"price_usd": 0,
"resolution": "HD",
"published_at": "2026-01-13T08:40:03.093248Z"
},
{
"yt_id": "NHbb37I0iYw",
"youtube_id": "NHbb37I0iYw",
"title": "Astana , Kazakhstan \ud83c\uddf0\ud83c\uddff | 4K Drone Footage",
"description": "Astana Kazakhstan \u2014 4K Drone Footage",
"tags": [
"cityscape",
"kazakhstan",
"astana"
],
"category": "cityscape",
"source": "youtube",
"status": "published",
"youtube_channel": "MTI Aerials",
"lat": 50.9897,
"lon": 71.21465,
"shot_lat": 50.9897,
"shot_lon": 71.21465,
"thumb_url": "https://i.ytimg.com/vi/NHbb37I0iYw/maxresdefault.jpg",
"ai_quality_score": 7,
"duration_s": 0,
"price_usd": 0,
"resolution": "HD",
"published_at": "2026-02-10T13:46:11.093248Z"
},
{
"yt_id": "2VYwf3QbSvU",
"youtube_id": "2VYwf3QbSvU",
"title": "LOST IN KAZAKHSTAN & KYRGYZSTAN | 4K | DRONE FOOTAGE",
"description": "Lost in Kazakhstan & Kyrgyzstan \u2014 4K Drone Footage",
"tags": [
"landscape",
"kazakhstan",
"kyrgyzstan"
],
"category": "landscape",
"source": "youtube",
"status": "published",
"youtube_channel": "Peter Ruck",
"lat": 43.7563,
"lon": 77.57585,
"shot_lat": 43.7563,
"shot_lon": 77.57585,
"thumb_url": "https://i.ytimg.com/vi/2VYwf3QbSvU/maxresdefault.jpg",
"ai_quality_score": 7,
"duration_s": 0,
"price_usd": 0,
"resolution": "HD",
"published_at": "2026-01-30T18:26:51.093248Z"
},
{
"yt_id": "9YYXgsf9FTs",
"youtube_id": "9YYXgsf9FTs",
"title": "\u30104K\u3011\ud83c\uddf0\ud83c\uddff Drone RAW Footage \ud83d\udd25 This is KAZAKHSTAN 2025 \ud83d\udd25 Almaty \ud83d\udd25 Astana & More \ud83d\udd25 UltraHD Stock Video",
"description": "Kazakhstan 4K \u2014 Almaty Astana Drone RAW Footage",
"tags": [
"cityscape",
"kazakhstan",
"almaty",
"astana"
],
"category": "cityscape",
"source": "youtube",
"status": "published",
"youtube_channel": "One Man Wolf Pack",
"lat": 42.7268,
"lon": 76.7436,
"shot_lat": 42.7268,
"shot_lon": 76.7436,
"thumb_url": "https://i.ytimg.com/vi/9YYXgsf9FTs/maxresdefault.jpg",
"ai_quality_score": 7,
"duration_s": 0,
"price_usd": 0,
"resolution": "HD",
"published_at": "2025-11-12T14:04:21.093248Z"
},
{
"yt_id": "ZkSxIbv_gbk",
"youtube_id": "ZkSxIbv_gbk",
"title": "Safari Tour, Africa \ud83c\uddf0\ud83c\uddea\ud83c\uddfa\ud83c\uddec\ud83c\uddf9\ud83c\uddff\ud83c\udde7\ud83c\uddfc\ud83c\uddf3\ud83c\udde6\ud83c\uddff\ud83c\udde6 - by drone [4K]",
"description": "Safari Tour Africa \u2014 Kenya Uganda Tanzania Botswana Namibia SA",
"tags": [
"wildlife",
"africa",
"safari"
],
"category": "wildlife",
"source": "youtube",
"status": "published",
"youtube_channel": "Drone Snap",
"lat": -2.23175,
"lon": 37.5634,
"shot_lat": -2.23175,
"shot_lon": 37.5634,
"thumb_url": "https://i.ytimg.com/vi/ZkSxIbv_gbk/maxresdefault.jpg",
"ai_quality_score": 7,
"duration_s": 0,
"price_usd": 0,
"resolution": "HD",
"published_at": "2025-09-19T21:05:18.093248Z"
},
{
"yt_id": "ZjFz9xSorVE",
"youtube_id": "ZjFz9xSorVE",
"title": "Best Drone Video of Botswana and Namibia. Africa",
"description": "Best Drone Video of Botswana and Namibia \u2014 Africa",
"tags": [
"landscape",
"botswana",
"namibia",
"africa"
],
"category": "landscape",
"source": "youtube",
"status": "published",
"youtube_channel": "Africa Luxury Travel and Wildlife",
"lat": -22.53295,
"lon": 21.8977,
"shot_lat": -22.53295,
"shot_lon": 21.8977,
"thumb_url": "https://i.ytimg.com/vi/ZjFz9xSorVE/maxresdefault.jpg",
"ai_quality_score": 7,
"duration_s": 0,
"price_usd": 0,
"resolution": "HD",
"published_at": "2026-02-24T18:45:26.093248Z"
},
{
"yt_id": "IGNYp3CflLg",
"youtube_id": "IGNYp3CflLg",
"title": "Ethiopia From Above - Africa Aerial View (Drone Film)",
"description": "Ethiopia From Above \u2014 Africa Aerial Drone Film",
"tags": [
"landscape",
"ethiopia",
"africa"
],
"category": "landscape",
"source": "youtube",
"status": "published",
"youtube_channel": "Stef Hoffer",
"lat": 9.7216,
"lon": 40.22345,
"shot_lat": 9.7216,
"shot_lon": 40.22345,
"thumb_url": "https://i.ytimg.com/vi/IGNYp3CflLg/maxresdefault.jpg",
"ai_quality_score": 7,
"duration_s": 0,
"price_usd": 0,
"resolution": "HD",
"published_at": "2025-10-06T02:08:49.093248Z"
},
{
"yt_id": "mQjfBvDf3m4",
"youtube_id": "mQjfBvDf3m4",
"title": "Best Drone Video of 2018 and 2019 in 4K UHD. Namibia, Botswana and South Africa.",
"description": "Best Drone Video Namibia Botswana South Africa \u2014 2018-2019 4K",
"tags": [
"landscape",
"namibia",
"botswana",
"south-africa"
],
"category": "landscape",
"source": "youtube",
"status": "published",
"youtube_channel": "Africa Luxury Travel and Wildlife",
"lat": -22.02045,
"lon": 19.57085,
"shot_lat": -22.02045,
"shot_lon": 19.57085,
"thumb_url": "https://i.ytimg.com/vi/mQjfBvDf3m4/maxresdefault.jpg",
"ai_quality_score": 7,
"duration_s": 0,
"price_usd": 0,
"resolution": "HD",
"published_at": "2025-09-27T14:32:56.093248Z"
},
{
"yt_id": "fzBVPKU_qX8",
"youtube_id": "fzBVPKU_qX8",
"title": "Breathtaking Drone Footage Filmed Throughout Africa | Rhino Africa",
"description": "Breathtaking Drone Footage Filmed Throughout Africa \u2014 Rhino",
"tags": [
"wildlife",
"africa",
"rhino"
],
"category": "wildlife",
"source": "youtube",
"status": "published",
"youtube_channel": "Rhino Africa Safaris",
"lat": -17.56395,
"lon": 29.23295,
"shot_lat": -17.56395,
"shot_lon": 29.23295,
"thumb_url": "https://i.ytimg.com/vi/fzBVPKU_qX8/maxresdefault.jpg",
"ai_quality_score": 7,
"duration_s": 0,
"price_usd": 0,
"resolution": "HD",
"published_at": "2025-06-20T08:37:46.093248Z"
},
{
"yt_id": "5U9fRmEYMUQ",
"youtube_id": "5U9fRmEYMUQ",
"title": "Incredible Aerial Footage of African Wildlife - Wild Botswana in 4K UHD (with Music)",
"description": "Incredible Aerial Footage of African Wildlife \u2014 Wild Botswana 4K",
"tags": [
"wildlife",
"botswana",
"africa"
],
"category": "wildlife",
"source": "youtube",
"status": "published",
"youtube_channel": "4K Relaxation Channel",
"lat": -22.3441,
"lon": 25.194,
"shot_lat": -22.3441,
"shot_lon": 25.194,
"thumb_url": "https://i.ytimg.com/vi/5U9fRmEYMUQ/maxresdefault.jpg",
"ai_quality_score": 7,
"duration_s": 0,
"price_usd": 0,
"resolution": "HD",
"published_at": "2026-01-01T20:01:17.093248Z"
},
{
"yt_id": "6yXuCf5tBlg",
"youtube_id": "6yXuCf5tBlg",
"title": "Amazing Wildlife Of AFRICA In 4K | Aerial Drone | Scenic Scenes Film",
"description": "Amazing Wildlife of Africa in 4K \u2014 Aerial Drone",
"tags": [
"wildlife",
"africa"
],
"category": "wildlife",
"source": "youtube",
"status": "published",
"youtube_channel": "Scenic Scenes",
"lat": -4.6241,
"lon": 34.3031,
"shot_lat": -4.6241,
"shot_lon": 34.3031,
"thumb_url": "https://i.ytimg.com/vi/6yXuCf5tBlg/maxresdefault.jpg",
"ai_quality_score": 7,
"duration_s": 0,
"price_usd": 0,
"resolution": "HD",
"published_at": "2026-03-02T21:04:27.093248Z"
},
{
"yt_id": "b6gbXsC4Fs0",
"youtube_id": "b6gbXsC4Fs0",
"title": "\u30104K\u3011Drone Footage | 5 MEGACITIES of Africa 2019 ..:: Cinematic Aerial Film",
"description": "5 Megacities of Africa 2019 \u2014 Cinematic Aerial Film 4K",
"tags": [
"cityscape",
"africa",
"megacity"
],
"category": "cityscape",
"source": "youtube",
"status": "published",
"youtube_channel": "One Man Wolf Pack",
"lat": 6.4407,
"lon": 3.6618,
"shot_lat": 6.4407,
"shot_lon": 3.6618,
"thumb_url": "https://i.ytimg.com/vi/b6gbXsC4Fs0/maxresdefault.jpg",
"ai_quality_score": 7,
"duration_s": 0,
"price_usd": 0,
"resolution": "HD",
"published_at": "2025-10-08T11:55:31.093248Z"
},
{
"yt_id": "2NYwewKYHB4",
"youtube_id": "2NYwewKYHB4",
"title": "Stunning Landscape of Leh Ladakh, Himalayas (Drone, 4k)",
"description": "Stunning Landscape of Leh Ladakh Himalayas \u2014 Drone 4K",
"tags": [
"mountain",
"india",
"ladakh",
"himalaya"
],
"category": "mountain",
"source": "youtube",
"status": "published",
"youtube_channel": "Tariq R",
"lat": 33.8304,
"lon": 76.86735,
"shot_lat": 33.8304,
"shot_lon": 76.86735,
"thumb_url": "https://i.ytimg.com/vi/2NYwewKYHB4/maxresdefault.jpg",
"ai_quality_score": 7,
"duration_s": 0,
"price_usd": 0,
"resolution": "HD",
"published_at": "2025-08-29T14:02:01.093248Z"
},
{
"yt_id": "Hjy2KQYiUUc",
"youtube_id": "Hjy2KQYiUUc",
"title": "Best Cinematic Drone shots | Ladakh India | Shot on DJI AIR 2S | 4K",
"description": "Best Cinematic Drone Shots Ladakh India \u2014 DJI AIR 2S 4K",
"tags": [
"mountain",
"india",
"ladakh"
],
"category": "mountain",
"source": "youtube",
"status": "published",
"youtube_channel": "Kanishk Gupta",
"lat": 33.46795,
"lon": 78.2922,
"shot_lat": 33.46795,
"shot_lon": 78.2922,
"thumb_url": "https://i.ytimg.com/vi/Hjy2KQYiUUc/maxresdefault.jpg",
"ai_quality_score": 7,
"duration_s": 0,
"price_usd": 0,
"resolution": "HD",
"published_at": "2025-05-05T01:28:40.093248Z"
},
{
"yt_id": "jS_BB1rcYV4",
"youtube_id": "jS_BB1rcYV4",
"title": "India 4K - Discover the Heart of Asia | Cinematic Drone Footage",
"description": "India 4K \u2014 Discover the Heart of Asia",
"tags": [
"landscape",
"india",
"cinematic"
],
"category": "landscape",
"source": "youtube",
"status": "published",
"youtube_channel": "Explore The World 4K",
"lat": 21.32135,
"lon": 79.3475,
"shot_lat": 21.32135,
"shot_lon": 79.3475,
"thumb_url": "https://i.ytimg.com/vi/jS_BB1rcYV4/maxresdefault.jpg",
"ai_quality_score": 7,
"duration_s": 0,
"price_usd": 0,
"resolution": "HD",
"published_at": "2026-02-25T20:12:02.093248Z"
},
{
"yt_id": "_cEv6W-3uWA",
"youtube_id": "_cEv6W-3uWA",
"title": "High Above | Drone Videos | Meghalaya, Kashmir, Arunachal, Ladakh",
"description": "Drone Videos \u2014 Meghalaya Kashmir Arunachal Ladakh",
"tags": [
"mountain",
"india",
"kashmir",
"ladakh",
"meghalaya"
],
"category": "mountain",
"source": "youtube",
"status": "published",
"youtube_channel": "Ethereal",
"lat": 33.6276,
"lon": 78.39375,
"shot_lat": 33.6276,
"shot_lon": 78.39375,
"thumb_url": "https://i.ytimg.com/vi/_cEv6W-3uWA/maxresdefault.jpg",
"ai_quality_score": 7,
"duration_s": 0,
"price_usd": 0,
"resolution": "HD",
"published_at": "2025-06-22T23:23:09.093248Z"
},
{
"yt_id": "XleHgd5mOec",
"youtube_id": "XleHgd5mOec",
"title": "Incredible India | Aerial Drone View  4k",
"description": "Incredible India \u2014 Aerial Drone View 4K",
"tags": [
"landscape",
"india"
],
"category": "landscape",
"source": "youtube",
"status": "published",
"youtube_channel": "Discover India",
"lat": 21.9873,
"lon": 77.6841,
"shot_lat": 21.9873,
"shot_lon": 77.6841,
"thumb_url": "https://i.ytimg.com/vi/XleHgd5mOec/maxresdefault.jpg",
"ai_quality_score": 7,
"duration_s": 0,
"price_usd": 0,
"resolution": "HD",
"published_at": "2026-02-04T16:56:31.093248Z"
},
{
"yt_id": "Y5-2ttBG0bU",
"youtube_id": "Y5-2ttBG0bU",
"title": "Leh Ladakh Drone and Cinematic Videos - 4K Ready",
"description": "Leh Ladakh \u2014 Drone and Cinematic Videos 4K",
"tags": [
"mountain",
"india",
"ladakh"
],
"category": "mountain",
"source": "youtube",
"status": "published",
"youtube_channel": "Bulu Pattnaik",
"lat": 33.4104,
"lon": 77.73255,
"shot_lat": 33.4104,
"shot_lon": 77.73255,
"thumb_url": "https://i.ytimg.com/vi/Y5-2ttBG0bU/maxresdefault.jpg",
"ai_quality_score": 7,
"duration_s": 0,
"price_usd": 0,
"resolution": "HD",
"published_at": "2025-08-10T02:48:57.093248Z"
},
{
"yt_id": "1CxMWmmvDhI",
"youtube_id": "1CxMWmmvDhI",
"title": "Alpine Lakes of Indian Himalayas | 4K Drone Footage",
"description": "Alpine Lakes of Indian Himalayas \u2014 4K Drone Footage",
"tags": [
"mountain",
"india",
"himalaya",
"alpine-lake"
],
"category": "mountain",
"source": "youtube",
"status": "published",
"youtube_channel": "Manav",
"lat": 32.91595,
"lon": 78.76655,
"shot_lat": 32.91595,
"shot_lon": 78.76655,
"thumb_url": "https://i.ytimg.com/vi/1CxMWmmvDhI/maxresdefault.jpg",
"ai_quality_score": 7,
"duration_s": 0,
"price_usd": 0,
"resolution": "HD",
"published_at": "2025-12-10T22:00:00.093248Z"
},
{
"yt_id": "JaV6UCa5ld0",
"youtube_id": "JaV6UCa5ld0",
"title": "MUNNAR \u25cf India \ud83c\uddee\ud83c\uddf3 \u30104K\u3011 Aerial Cinematic Drone",
"description": "Munnar India \u2014 4K Aerial Cinematic Drone",
"tags": [
"forest",
"india",
"kerala",
"munnar"
],
"category": "forest",
"source": "youtube",
"status": "published",
"youtube_channel": "Travel Penguin",
"lat": 10.67495,
"lon": 76.497,
"shot_lat": 10.67495,
"shot_lon": 76.497,
"thumb_url": "https://i.ytimg.com/vi/JaV6UCa5ld0/maxresdefault.jpg",
"ai_quality_score": 7,
"duration_s": 0,
"price_usd": 0,
"resolution": "HD",
"published_at": "2025-04-26T11:47:46.093248Z"
},
{
"yt_id": "PYKf0T-RZ8o",
"youtube_id": "PYKf0T-RZ8o",
"title": "ULURU DRONE FOOTAGE AUSTRALIA - 4K",
"description": "Uluru Drone Footage Australia \u2014 4K",
"tags": [
"landscape",
"australia",
"uluru",
"outback"
],
"category": "landscape",
"source": "youtube",
"status": "published",
"youtube_channel": "Alexander ND TraveLLer",
"lat": -25.1758,
"lon": 131.00975,
"shot_lat": -25.1758,
"shot_lon": 131.00975,
"thumb_url": "https://i.ytimg.com/vi/PYKf0T-RZ8o/maxresdefault.jpg",
"ai_quality_score": 7,
"duration_s": 0,
"price_usd": 0,
"resolution": "HD",
"published_at": "2026-01-09T08:00:49.093248Z"
},
{
"yt_id": "JQhHg6lXhkI",
"youtube_id": "JQhHg6lXhkI",
"title": "Sacred & Stunning | The First Drone Footage of Kata Tjuta",
"description": "Stunning Drone Footage of Kata Tjuta \u2014 Red Centre",
"tags": [
"landscape",
"australia",
"kata-tjuta",
"outback"
],
"category": "landscape",
"source": "youtube",
"status": "published",
"youtube_channel": "Ayers Rock Resort",
"lat": -25.0942,
"lon": 130.9094,
"shot_lat": -25.0942,
"shot_lon": 130.9094,
"thumb_url": "https://i.ytimg.com/vi/JQhHg6lXhkI/maxresdefault.jpg",
"ai_quality_score": 7,
"duration_s": 0,
"price_usd": 0,
"resolution": "HD",
"published_at": "2025-10-17T21:10:01.093248Z"
},
{
"yt_id": "3l0MWlojX3w",
"youtube_id": "3l0MWlojX3w",
"title": "Uluru and Kata Tjuta aerial drone video",
"description": "Uluru and Kata Tjuta \u2014 Aerial Drone Video",
"tags": [
"landscape",
"australia",
"uluru",
"outback"
],
"category": "landscape",
"source": "youtube",
"status": "published",
"youtube_channel": "Australia's Northern Territory",
"lat": -25.5836,
"lon": 130.70625,
"shot_lat": -25.5836,
"shot_lon": 130.70625,
"thumb_url": "https://i.ytimg.com/vi/3l0MWlojX3w/maxresdefault.jpg",
"ai_quality_score": 7,
"duration_s": 0,
"price_usd": 0,
"resolution": "HD",
"published_at": "2025-04-27T10:06:37.093248Z"
},
{
"yt_id": "-2_Ic7XWXLg",
"youtube_id": "-2_Ic7XWXLg",
"title": "4K Drone Video -  The Outback | Australia | Northern Territory",
"description": "4K Drone Video \u2014 The Outback Northern Territory Australia",
"tags": [
"desert",
"australia",
"outback",
"northern-territory"
],
"category": "desert",
"source": "youtube",
"status": "published",
"youtube_channel": "Drive & Time",
"lat": -19.4169,
"lon": 133.8354,
"shot_lat": -19.4169,
"shot_lon": 133.8354,
"thumb_url": "https://i.ytimg.com/vi/-2_Ic7XWXLg/maxresdefault.jpg",
"ai_quality_score": 7,
"duration_s": 0,
"price_usd": 0,
"resolution": "HD",
"published_at": "2026-02-13T13:23:39.093248Z"
},
{
"yt_id": "Yo4ueevKfdE",
"youtube_id": "Yo4ueevKfdE",
"title": "New Zealand - 'The Adventure' by Drone (4K)",
"description": "New Zealand The Adventure \u2014 by Drone 4K",
"tags": [
"landscape",
"new-zealand",
"adventure"
],
"category": "landscape",
"source": "youtube",
"status": "published",
"youtube_channel": "Man And Drone",
"lat": -44.19815,
"lon": 170.62655,
"shot_lat": -44.19815,
"shot_lon": 170.62655,
"thumb_url": "https://i.ytimg.com/vi/Yo4ueevKfdE/maxresdefault.jpg",
"ai_quality_score": 7,
"duration_s": 0,
"price_usd": 0,
"resolution": "HD",
"published_at": "2025-08-07T09:48:14.093248Z"
},
{
"yt_id": "K5XRprbteF4",
"youtube_id": "K5XRprbteF4",
"title": "New Zealand 25 Minute Drone Epic (4K)",
"description": "New Zealand 25-Minute Drone Epic 4K",
"tags": [
"landscape",
"new-zealand",
"epic"
],
"category": "landscape",
"source": "youtube",
"status": "published",
"youtube_channel": "Man And Drone",
"lat": -38.4536,
"lon": 175.6057,
"shot_lat": -38.4536,
"shot_lon": 175.6057,
"thumb_url": "https://i.ytimg.com/vi/K5XRprbteF4/maxresdefault.jpg",
"ai_quality_score": 7,
"duration_s": 0,
"price_usd": 0,
"resolution": "HD",
"published_at": "2025-10-23T17:43:17.093248Z"
},
{
"yt_id": "lMU1JcIwnOg",
"youtube_id": "lMU1JcIwnOg",
"title": "Amazing Australia 4K: Drone Footage with Relaxing Music",
"description": "Breathtaking Australia Aerial Views \u2014 Relaxing 4K Drone",
"tags": [
"landscape",
"australia",
"cinematic"
],
"category": "landscape",
"source": "youtube",
"status": "published",
"youtube_channel": "My World Circle",
"lat": -25.61665,
"lon": 134.26005,
"shot_lat": -25.61665,
"shot_lon": 134.26005,
"thumb_url": "https://i.ytimg.com/vi/lMU1JcIwnOg/maxresdefault.jpg",
"ai_quality_score": 7,
"duration_s": 0,
"price_usd": 0,
"resolution": "HD",
"published_at": "2025-06-28T02:21:24.093248Z"
},
{
"yt_id": "oCTFmGENO-M",
"youtube_id": "oCTFmGENO-M",
"title": "Bangkok, Thailand from Above in 4K \u2014 A Cinematic Drone Journey",
"description": "Bangkok Thailand from Above 4K \u2014 Cinematic Drone",
"tags": [
"cityscape",
"thailand",
"bangkok"
],
"category": "cityscape",
"source": "youtube",
"status": "published",
"youtube_channel": "Alejandro Torres",
"lat": 13.8751,
"lon": 100.89525,
"shot_lat": 13.8751,
"shot_lon": 100.89525,
"thumb_url": "https://i.ytimg.com/vi/oCTFmGENO-M/maxresdefault.jpg",
"ai_quality_score": 7,
"duration_s": 0,
"price_usd": 0,
"resolution": "HD",
"published_at": "2025-12-07T01:26:21.093248Z"
},
{
"yt_id": "w92n013BDpc",
"youtube_id": "w92n013BDpc",
"title": "A Cinematic Drone Journey Over Phi Phi Islands, Thailand in 4K",
"description": "Phi Phi Islands Thailand \u2014 4K Drone Footage",
"tags": [
"ocean",
"thailand",
"phi-phi",
"island"
],
"category": "ocean",
"source": "youtube",
"status": "published",
"youtube_channel": "Alejandro Torres",
"lat": 8.02965,
"lon": 98.2998,
"shot_lat": 8.02965,
"shot_lon": 98.2998,
"thumb_url": "https://i.ytimg.com/vi/w92n013BDpc/maxresdefault.jpg",
"ai_quality_score": 7,
"duration_s": 0,
"price_usd": 0,
"resolution": "HD",
"published_at": "2025-07-09T19:40:36.093248Z"
},
{
"yt_id": "8sjIPtW53kk",
"youtube_id": "8sjIPtW53kk",
"title": "75 Minutes of Bali, Indonesia: Beautiful Aerial Drone Stock Video Footage in 4K",
"description": "75 Minutes of Bali Indonesia \u2014 Aerial Drone 4K",
"tags": [
"landscape",
"indonesia",
"bali"
],
"category": "landscape",
"source": "youtube",
"status": "published",
"youtube_channel": "21Aerials",
"lat": -7.979,
"lon": 114.447,
"shot_lat": -7.979,
"shot_lon": 114.447,
"thumb_url": "https://i.ytimg.com/vi/8sjIPtW53kk/maxresdefault.jpg",
"ai_quality_score": 7,
"duration_s": 0,
"price_usd": 0,
"resolution": "HD",
"published_at": "2025-12-18T16:26:03.093248Z"
},
{
"yt_id": "VKL0AKnSeto",
"youtube_id": "VKL0AKnSeto",
"title": "Krabi 8K Drone Footage | Tiger Cave Temple, Mythic Peaks & Endless Tides UHD",
"description": "Krabi 8K Drone \u2014 Tiger Cave Temple & Mythic Peaks",
"tags": [
"ruins-heritage",
"thailand",
"krabi",
"temple"
],
"category": "ruins-heritage",
"source": "youtube",
"status": "published",
"youtube_channel": "Ocean Deep Chill",
"lat": 7.97305,
"lon": 98.7842,
"shot_lat": 7.97305,
"shot_lon": 98.7842,
"thumb_url": "https://i.ytimg.com/vi/VKL0AKnSeto/maxresdefault.jpg",
"ai_quality_score": 7,
"duration_s": 0,
"price_usd": 0,
"resolution": "HD",
"published_at": "2025-05-03T08:38:48.093248Z"
},
{
"yt_id": "6btYMU9cfao",
"youtube_id": "6btYMU9cfao",
"title": "Best of BANGKOK From the SKY by Drone \ud83c\uddf9\ud83c\udded Thailand",
"description": "Best of Bangkok from the Sky \u2014 Drone Thailand",
"tags": [
"cityscape",
"thailand",
"bangkok"
],
"category": "cityscape",
"source": "youtube",
"status": "published",
"youtube_channel": "Global Travel Mate",
"lat": 14.21725,
"lon": 100.7424,
"shot_lat": 14.21725,
"shot_lon": 100.7424,
"thumb_url": "https://i.ytimg.com/vi/6btYMU9cfao/maxresdefault.jpg",
"ai_quality_score": 7,
"duration_s": 0,
"price_usd": 0,
"resolution": "HD",
"published_at": "2026-02-22T03:20:58.093248Z"
},
{
"yt_id": "xufcrZgJx4E",
"youtube_id": "xufcrZgJx4E",
"title": "Thailand 4K - Tropical Beauty from the Sky | Cinematic Drone Footage",
"description": "Thailand 4K \u2014 Tropical Beauty from the Sky",
"tags": [
"landscape",
"thailand",
"tropical"
],
"category": "landscape",
"source": "youtube",
"status": "published",
"youtube_channel": "Explore The World 4K",
"lat": 12.56995,
"lon": 99.97545,
"shot_lat": 12.56995,
"shot_lon": 99.97545,
"thumb_url": "https://i.ytimg.com/vi/xufcrZgJx4E/maxresdefault.jpg",
"ai_quality_score": 7,
"duration_s": 0,
"price_usd": 0,
"resolution": "HD",
"published_at": "2026-01-29T17:34:00.093248Z"
},
{
"yt_id": "SLYUsZgFPJQ",
"youtube_id": "SLYUsZgFPJQ",
"title": "\u30104K\u3011\ud83c\uddf5\ud83c\udded Drone Footage \ud83d\udd25 Cebu City - Philippines \ud83d\udd25 Cinematic Aerial Film",
"description": "Cebu City Philippines 2019 \u2014 Cinematic Aerial 4K",
"tags": [
"cityscape",
"philippines",
"cebu"
],
"category": "cityscape",
"source": "youtube",
"status": "published",
"youtube_channel": "One Man Wolf Pack",
"lat": 10.32155,
"lon": 123.7582,
"shot_lat": 10.32155,
"shot_lon": 123.7582,
"thumb_url": "https://i.ytimg.com/vi/SLYUsZgFPJQ/maxresdefault.jpg",
"ai_quality_score": 7,
"duration_s": 0,
"price_usd": 0,
"resolution": "HD",
"published_at": "2025-06-08T12:12:14.093248Z"
},
{
"yt_id": "QzasfZ-Sr2k",
"youtube_id": "QzasfZ-Sr2k",
"title": "Indonesia 4K - Journey Through Paradise | Cinematic Drone Footage",
"description": "Indonesia 4K \u2014 Journey Through Paradise",
"tags": [
"landscape",
"indonesia",
"paradise"
],
"category": "landscape",
"source": "youtube",
"status": "published",
"youtube_channel": "Explore The World 4K",
"lat": -2.60785,
"lon": 118.495,
"shot_lat": -2.60785,
"shot_lon": 118.495,
"thumb_url": "https://i.ytimg.com/vi/QzasfZ-Sr2k/maxresdefault.jpg",
"ai_quality_score": 7,
"duration_s": 0,
"price_usd": 0,
"resolution": "HD",
"published_at": "2025-05-31T23:31:32.093248Z"
}
]